Metadata-Version: 2.1
Name: Agrothon
Version: 1.3.2
Summary: A Farm Monitoring Bot
Home-page: https://github.com/viswanathbalusu/agrothon
Author: viswanathbalusu
Author-email: ckvbalusu@gmail.com
License: GPL3.0
Platform: any
Classifier: Programming Language :: Python :: 3
Classifier: Programming Language :: Python :: 3.8
Classifier: License :: OSI Approved :: GNU General Public License (GPL)
Classifier: Operating System :: POSIX :: Linux
Classifier: Development Status :: 5 - Production/Stable
Requires-Python: >=3.8
Requires-Dist: pyrogram (==1.2.9)
Requires-Dist: tgcrypto (==1.2.2)
Requires-Dist: motor (==2.4.0)
Requires-Dist: fastapi[all] (==0.64.0)
Requires-Dist: requests (==2.25.1)
Requires-Dist: python-dotenv (==0.17.0)
Requires-Dist: aiohttp (==3.7.4.post0)
Requires-Dist: python-telegram-bot (==13.5)
Requires-Dist: pandas (==1.2.4)
Requires-Dist: numpy (==1.19.5)
Requires-Dist: tensorflow (==2.4.1)
Requires-Dist: prettytable (==2.1.0)
Requires-Dist: opencv-python (==4.5.1.48)
Requires-Dist: pillow (==8.2.0)
Requires-Dist: seaborn (==0.11.1)
Requires-Dist: Keras (==2.4.3)
Requires-Dist: scikit-learn (==0.22.2.post1)
Requires-Dist: telegraph (==1.4.1)
Requires-Dist: psutil (==5.8.0)
